csb_validator/__init__.py
csb_validator/__main__.py
csb_validator/cli.py
csb_validator/line_mapper.py
csb_validator/pdf_writer.py
csb_validator/runner.py
csb_validator/validator_crowbar.py
csb_validator/validator_trusted.py
csb_validator-2.2.1.dist-info/licenses/LICENSE
csb_validator-2.2.1.dist-info/METADATA
csb_validator-2.2.1.dist-info/WHEEL
csb_validator-2.2.1.dist-info/entry_points.txt
csb_validator-2.2.1.dist-info/top_level.txt
csb_validator-2.2.1.dist-info/RECORD
