Metadata-Version: 2.4
Name: csb-validator
Version: 2.2.1
Summary: Validate CSB (Crowdsourced Bathymetry) GeoJSON and other formats
Home-page: https://github.com/CI-CMG/csb-validator
Author: Clinton Campbell
Author-email: clint.campbell@colorado.edu
Classifier: Programming Language :: Python :: 3
Classifier: License :: OSI Approved :: MIT License
Classifier: Operating System :: OS Independent
Requires-Python: >=3.7
License-File: LICENSE
Requires-Dist: aiofiles
Requires-Dist: fpdf
Requires-Dist: colorama
Requires-Dist: csbschema
Provides-Extra: trusted-node
Requires-Dist: csbschema; extra == "trusted-node"
Dynamic: author
Dynamic: author-email
Dynamic: classifier
Dynamic: home-page
Dynamic: license-file
Dynamic: provides-extra
Dynamic: requires-dist
Dynamic: requires-python
Dynamic: summary
